django_tags_select_input/__init__.py
django_tags_select_input/admin.py
django_tags_select_input/apps.py
django_tags_select_input/models.py
django_tags_select_input/tests.py
django_tags_select_input/views.py
django_tags_select_input/forms/__init__.py
django_tags_select_input/forms/widgets/__init__.py
django_tags_select_input/migrations/__init__.py
django_tags_select_input-0.1.1600119747.dist-info/METADATA
django_tags_select_input-0.1.1600119747.dist-info/WHEEL
django_tags_select_input-0.1.1600119747.dist-info/top_level.txt
django_tags_select_input-0.1.1600119747.dist-info/RECORD
